aplos_nca_saas_sdk/__init__.py
aplos_nca_saas_sdk/run_analysis_execution.py
aplos_nca_saas_sdk/version.py
aplos_nca_saas_sdk/integration_testing/example_main.py
aplos_nca_saas_sdk/integration_testing/integration_test_base.py
aplos_nca_saas_sdk/integration_testing/integration_test_configurations.py
aplos_nca_saas_sdk/integration_testing/integration_test_factory.py
aplos_nca_saas_sdk/integration_testing/integration_test_response.py
aplos_nca_saas_sdk/integration_testing/integration_test_suite.py
aplos_nca_saas_sdk/integration_testing/readme.md
aplos_nca_saas_sdk/integration_testing/configs/_config_base.py
aplos_nca_saas_sdk/integration_testing/configs/app_settings_config.py
aplos_nca_saas_sdk/integration_testing/configs/config_sample.json
aplos_nca_saas_sdk/integration_testing/configs/file_upload_config.py
aplos_nca_saas_sdk/integration_testing/configs/login_config.py
aplos_nca_saas_sdk/integration_testing/configs/nca_execution_config.py
aplos_nca_saas_sdk/integration_testing/configs/nca_validation_config.py
aplos_nca_saas_sdk/integration_testing/files/executions/config1.json
aplos_nca_saas_sdk/integration_testing/files/uploads/input1.csv
aplos_nca_saas_sdk/integration_testing/files/uploads/input1.dat
aplos_nca_saas_sdk/integration_testing/files/uploads/input1.sas7bdat
aplos_nca_saas_sdk/integration_testing/files/uploads/input1.xls
aplos_nca_saas_sdk/integration_testing/files/uploads/input1.xlsx
aplos_nca_saas_sdk/integration_testing/files/uploads/input1.xpt
aplos_nca_saas_sdk/integration_testing/tests/app_configuration_test.py
aplos_nca_saas_sdk/integration_testing/tests/app_login_test.py
aplos_nca_saas_sdk/integration_testing/tests/file_upload_test.py
aplos_nca_saas_sdk/integration_testing/tests/nca_analysis_test.py
aplos_nca_saas_sdk/integration_testing/tests/nca_analysis_validation_test.py
aplos_nca_saas_sdk/nca_resources/_api_base.py
aplos_nca_saas_sdk/nca_resources/aws_cognito.py
aplos_nca_saas_sdk/nca_resources/aws_s3_presigned_payload.py
aplos_nca_saas_sdk-0.0.25.dist-info/METADATA
aplos_nca_saas_sdk-0.0.25.dist-info/WHEEL
aplos_nca_saas_sdk-0.0.25.dist-info/licenses/LICENSE
aplos_nca_saas_sdk-0.0.25.dist-info/RECORD
