Metadata-Version: 2.4
Name: aplos_nca_saas_sdk
Version: 0.0.25
Summary: Aplos NCA SaaS SDK
Project-URL: Homepage, https://aplosanalytics.com/
Project-URL: Documentation, https://docs.aplosanalytics.com/
Project-URL: Repository, https://github.com/AplosAnalytics/Aplos-NCA-SaaS-SDK
Project-URL: Issues, https://github.com/AplosAnalytics/Aplos-NCA-SaaS-SDK/issues
Author-email: Eric Wilson <eric.wilson@aplosanalytics.com>
License: MIT License
License-File: LICENSE
Keywords: Bioavailability Studies,Bioequivalence Studies,Clinical Pharmacology,Clinical Trials,Dose-Proportionality Studies,Drug Interaction Studies,NCA,Non-Compartmental Analysis,PK Analysis,PK modeling,Pharma Data Analysis,Pharmacokinetic Analysis,Pharmacokinetics,Pharmacokinetics Software,SaaS
Classifier: Development Status :: 4 - Beta
Classifier: Intended Audience :: Developers
Classifier: License :: OSI Approved :: MIT License
Classifier: Operating System :: OS Independent
Classifier: Programming Language :: Python :: 3
Classifier: Topic :: Software Development :: Libraries
Requires-Python: >=3.10
Requires-Dist: aws-lambda-powertools>=3.3.0
Requires-Dist: boto3>=1.34.110
Requires-Dist: mypy-boto3-cognito-idp>=1.35.68
Requires-Dist: pyjwt>=2.9.0
Requires-Dist: python-dotenv>=1.0.1
Requires-Dist: requests>=2.31.0
